mcp_rs_publish/__init__.py
mcp_rs_publish/command.py
mcp_rs_publish-0.1.7.dist-info/METADATA
mcp_rs_publish-0.1.7.dist-info/WHEEL
mcp_rs_publish-0.1.7.dist-info/entry_points.txt
mcp_rs_publish-0.1.7.dist-info/top_level.txt
mcp_rs_publish-0.1.7.dist-info/RECORD
