Metadata-Version: 2.4
Name: mcp_rs_publish
Version: 0.1.7
Summary: mcp_rs_publish
Requires-Python: >=3.13
Requires-Dist: mcp[cli]>=1.13.1
